karrio/mappers/fedex/__init__.py
karrio/mappers/fedex/mapper.py
karrio/mappers/fedex/proxy.py
karrio/mappers/fedex/settings.py
karrio/plugins/fedex/__init__.py
karrio/providers/fedex/__init__.py
karrio/providers/fedex/document.py
karrio/providers/fedex/error.py
karrio/providers/fedex/rate.py
karrio/providers/fedex/tracking.py
karrio/providers/fedex/units.py
karrio/providers/fedex/utils.py
karrio/providers/fedex/pickup/__init__.py
karrio/providers/fedex/pickup/cancel.py
karrio/providers/fedex/pickup/create.py
karrio/providers/fedex/pickup/update.py
karrio/providers/fedex/shipment/__init__.py
karrio/providers/fedex/shipment/cancel.py
karrio/providers/fedex/shipment/create.py
karrio/schemas/fedex/__init__.py
karrio/schemas/fedex/cancel_pickup_request.py
karrio/schemas/fedex/cancel_pickup_response.py
karrio/schemas/fedex/cancel_request.py
karrio/schemas/fedex/cancel_response.py
karrio/schemas/fedex/error_response.py
karrio/schemas/fedex/paperless_request.py
karrio/schemas/fedex/paperless_response.py
karrio/schemas/fedex/pickup_request.py
karrio/schemas/fedex/pickup_response.py
karrio/schemas/fedex/rating_request.py
karrio/schemas/fedex/rating_responses.py
karrio/schemas/fedex/shipping_request.py
karrio/schemas/fedex/shipping_responses.py
karrio/schemas/fedex/tracking_document_request.py
karrio/schemas/fedex/tracking_document_response.py
karrio/schemas/fedex/tracking_request.py
karrio/schemas/fedex/tracking_response.py
karrio_fedex-2026.1.4.dist-info/METADATA
karrio_fedex-2026.1.4.dist-info/WHEEL
karrio_fedex-2026.1.4.dist-info/entry_points.txt
karrio_fedex-2026.1.4.dist-info/top_level.txt
karrio_fedex-2026.1.4.dist-info/RECORD
